{
    "fcast_si_hint": {
        "articleinfo": {
            "pubdate": "Sunday, 3.1.2021 ob 9h", 
            "title": "Vremenski namig", 
            "tsValid_issued": "2021-01-03 09:30"
        }, 
        "section": [
            {
                "id": "fcast_SLOVENIA_d1", 
                "para": [
                    {
                        "para": "Snega je zlasti v Julijskih Alpah ogromno, marsikje tako debele sne\u017ene odeje 3. januarja ni bilo ve\u010d desetletij: Kr\u2026 https://t.co/XygP44RfoU"
                    }
                ], 
                "title": "Zadnja novica"
            }
        ]
    }, 
    "fcast_si_text": {
        "articleinfo": {
            "pubdate": "Nedelja, 3.1.2021 ob 11h", 
            "title": "Vremenska napoved", 
            "tsValid_issued": "2021-01-03 10:42"
        }, 
        "dataType": "", 
        "features": "", 
        "params": "", 
        "section": [
            {
                "para": "Popoldne bo prete\u017eno obla\u010dno, ob\u010dasno bodo manj\u0161e krajevne padavine, deloma plohe. Najvi\u0161je dnevne temperature bodo od 2 do 7, na Primorskem do 11 \u00b0C.", 
                "title": "NAPOVED ZA SLOVENIJO"
            }, 
            {
                "para": "Jutri bo prete\u017eno obla\u010dno in zjutraj po nekaterih ni\u017einah megleno. Pojavljale se bodo manj\u0161e krajevne plohe, ki bodo verjetnej\u0161e v zahodni polovici Slovenije. Najni\u017eje jutranje temperature bodo od -1 do 3, v alpskih dolinah okoli -4, ob morju 5, najvi\u0161je dnevne od 0 do 6, na Primorskem do 10 \u00b0C.", 
                "title": "NAPOVED ZA SLOVENIJO"
            }, 
            {
                "para": "Popoldne in jutri bo prete\u017eno obla\u010dno, ob\u010dasno bodo \u0161e krajevne padavine, ki bodo pogostej\u0161e v krajih zahodno in ju\u017eno od nas.", 
                "title": "NAPOVED ZA SOSEDNJE POKRAJINE"
            }, 
            {
                "title": "NAPOVED ZA SOSEDNJE POKRAJINE"
            }, 
            {
                "para": "Nad severnim Sredozemljem je obmo\u010dje nizkega zra\u010dnega tlaka, ki se po\u010dasi polni. Za vremensko fronto \u0161e naprej od juga priteka nad na\u0161e kraje razmeroma vla\u017een zrak.", 
                "title": "VREMENSKA SLIKA"
            }, 
            {
                "para": "Jutri Nad osrednjim Sredozemljem je plitvo obmo\u010dje nizkega zra\u010dnega tlaka. Nad Balkanom se zadr\u017euje vremenska fronta. S \u0161ibkimi ju\u017enimi vetrovi doteka k nam vla\u017een in postopno nekoliko hladnej\u0161i zrak.", 
                "title": "VREMENSKA SLIKA"
            }, 
            {
                "para": "V torek bo prete\u017eno obla\u010dno in zjutraj ponekod po ni\u017einah megleno, nekaj sonca bo ob\u010dasno predvsem v vi\u0161jih legah ter na Primorskem. Ve\u010dinoma suho bo, na Primorskem bo zapihala \u0161ibka burja. Zve\u010der in v no\u010di na sredo bodo padavine od juga prehodno zajele vso Slovenijo in do srede zjutraj ve\u010dinoma ponehale. Po ni\u017einah bo deloma de\u017eevalo deloma sne\u017eilo. \u010cez dan bo spremenljivo do prete\u017eno obla\u010dno s posameznimi plohami.", 
                "title": "OBETI"
            }, 
            {
                "para": "Predvsem v visokogorju Julijskih Alp je velika nevarnost sne\u017enih plazov.", 
                "title": "OPOZORILO"
            }, 
            {
                "para": "Popoldne in jutri bo prete\u017eno obla\u010dno, pojavljale se bodo predvsem krajevne plohe.", 
                "title": "NAPOVED ZA SLOVENIJO - povzetek"
            }
        ], 
        "tsUpdated": "2021-01-03T09:42:37+00:00", 
        "type": "FeatureCollection"
    }, 
    "observation_si_avio": {
        "dataType": "observation", 
        "features": [
            {
                "geometry": {
                    "coordinates": [
                        15.525, 
                        45.893599999999999
                    ], 
                    "type": "Point"
                }, 
                "properties": {
                    "altitude": "154.0", 
                    "country": "SI", 
                    "days": [
                        {
                            "UTCoffset": "+01:00", 
                            "date": "2021-01-03", 
                            "timeline": [
                                {
                                    "clouds_icon_wwsyn_icon": "overcast_lightFG_day", 
                                    "interval": "", 
                                    "time": "600", 
                                    "valid": "2021-01-03T09:00:00+00:00", 
                                    "vis_shortText": "1-5", 
                                    "wwsyn_icon": "lightFG"
                                }
                            ]
                        }
                    ], 
                    "id": "CERKLJE_LETAL-SCE_", 
                    "parentId": "SI_SPODNJEPOSAVSKA_", 
                    "title": "Letali\u0161\u010de Cerklje ob Krki"
                }, 
                "type": "Feature"
            }, 
            {
                "geometry": {
                    "coordinates": [
                        15.6869, 
                        46.479999999999997
                    ], 
                    "type": "Point"
                }, 
                "properties": {
                    "altitude": "264.0", 
                    "country": "SI", 
                    "days": [
                        {
                            "UTCoffset": "+01:00", 
                            "date": "2021-01-03", 
                            "timeline": [
                                {
                                    "clouds_icon_wwsyn_icon": "overcast_day", 
                                    "interval": "", 
                                    "time": "600", 
                                    "valid": "2021-01-03T09:00:00+00:00", 
                                    "vis_shortText": "5-10", 
                                    "wwsyn_icon": ""
                                }
                            ]
                        }
                    ], 
                    "id": "MARIBOR_SLIVNICA_", 
                    "parentId": "SI_PODRAVSKA_", 
                    "title": "Letali\u0161\u010de Edvarda Rusjana Maribor"
                }, 
                "type": "Feature"
            }, 
            {
                "geometry": {
                    "coordinates": [
                        14.477499999999999, 
                        46.217799999999997
                    ], 
                    "type": "Point"
                }, 
                "properties": {
                    "altitude": "364.0", 
                    "country": "SI", 
                    "days": [
                        {
                            "UTCoffset": "+01:00", 
                            "date": "2021-01-03", 
                            "timeline": [
                                {
                                    "clouds_icon_wwsyn_icon": "overcast_day", 
                                    "interval": "", 
                                    "time": "600", 
                                    "valid": "2021-01-03T09:00:00+00:00", 
                                    "vis_shortText": "5-10", 
                                    "wwsyn_icon": ""
                                }
                            ]
                        }
                    ], 
                    "id": "LJUBL-ANA_BRNIK_", 
                    "parentId": "SI_GORENJSKA_", 
                    "title": "Letali\u0161\u010de Jo\u017eeta Pu\u010dnika Ljubljana"
                }, 
                "type": "Feature"
            }, 
            {
                "geometry": {
                    "coordinates": [
                        13.6206, 
                        45.4756
                    ], 
                    "type": "Point"
                }, 
                "properties": {
                    "altitude": "2.0", 
                    "country": "SI", 
                    "days": [
                        {
                            "UTCoffset": "+01:00", 
                            "date": "2021-01-03", 
                            "timeline": [
                                {
                                    "clouds_icon_wwsyn_icon": "partCloudy_day", 
                                    "interval": "", 
                                    "time": "600", 
                                    "valid": "2021-01-03T09:00:00+00:00", 
                                    "vis_shortText": ">10", 
                                    "wwsyn_icon": ""
                                }
                            ]
                        }
                    ], 
                    "id": "PORTOROZ_SECOVLJE_", 
                    "parentId": "SI_OBALNO-KRASKA_", 
                    "title": "Letali\u0161\u010de Portoro\u017e"
                }, 
                "type": "Feature"
            }
        ], 
        "icon_format": "png", 
        "icon_url_base": "http://www.meteo.si/uploads/meteo/style/img/weather/", 
        "language": "sl", 
        "params": {
            "clouds_icon_wwsyn_icon": {
                "desc": "Obla\u010dnost / Pojavi", 
                "name": "NPHENOM.", 
                "unit": ""
            }, 
            "vis_shortText": {
                "desc": "Vidnost", 
                "name": "VIS", 
                "unit": "km"
            }, 
            "wwsyn_icon": {
                "desc": "Pojavi", 
                "name": "PHENOM.", 
                "unit": ""
            }
        }, 
        "tsUpdated": "2021-01-03T09:13:04+00:00", 
        "type": "FeatureCollection", 
        "webcamUrl": "http://www.meteo.si/uploads/probase/www/observ/webcam/"
    }, 
    "observation_si_eco": {
        "dataType": "observationAms", 
        "features": [
            {
                "geometry": {
                    "coordinates": [
                        15.2257, 
                        46.236499999999999
                    ], 
                    "type": "Point"
                }, 
                "properties": {
                    "altitude": "244.0", 
                    "country": "SI", 
                    "days": [
                        {
                            "UTCoffset": "+01:00", 
                            "date": "2021-01-03", 
                            "timeline": [
                                {
                                    "interval": "", 
                                    "no2_val": "", 
                                    "pm10_val": "21", 
                                    "time": "600", 
                                    "valid": "2021-01-03T09:00:00+00:00"
                                }
                            ]
                        }
                    ], 
                    "id": "METEO-1025_", 
                    "parentId": "SI_SAVINJSKA_", 
                    "title": "Celje"
                }, 
                "type": "Feature"
            }, 
            {
                "geometry": {
                    "coordinates": [
                        14.5124, 
                        46.0655
                    ], 
                    "type": "Point"
                }, 
                "properties": {
                    "altitude": "299.0", 
                    "country": "SI", 
                    "days": [
                        {
                            "UTCoffset": "+01:00", 
                            "date": "2021-01-03", 
                            "timeline": [
                                {
                                    "interval": "", 
                                    "no2_val": "18", 
                                    "pm10_val": "14", 
                                    "time": "600", 
                                    "valid": "2021-01-03T09:00:00+00:00"
                                }
                            ]
                        }
                    ], 
                    "id": "METEO-1005_", 
                    "parentId": "SI_OSREDNJESLOVENSKA_", 
                    "title": "Ljubljana"
                }, 
                "type": "Feature"
            }, 
            {
                "geometry": {
                    "coordinates": [
                        16.191299999999998, 
                        46.652099999999997
                    ], 
                    "type": "Point"
                }, 
                "properties": {
                    "altitude": "188.0", 
                    "country": "SI", 
                    "days": [
                        {
                            "UTCoffset": "+01:00", 
                            "date": "2021-01-03", 
                            "timeline": [
                                {
                                    "interval": "", 
                                    "no2_val": "11", 
                                    "pm10_val": "33", 
                                    "time": "600", 
                                    "valid": "2021-01-03T09:00:00+00:00"
                                }
                            ]
                        }
                    ], 
                    "id": "METEO-1444_", 
                    "parentId": "SI_POMURSKA_", 
                    "title": "Murska Sobota"
                }, 
                "type": "Feature"
            }, 
            {
                "geometry": {
                    "coordinates": [
                        13.6524, 
                        45.955599999999997
                    ], 
                    "type": "Point"
                }, 
                "properties": {
                    "altitude": "113", 
                    "country": "SI", 
                    "days": [
                        {
                            "UTCoffset": "+01:00", 
                            "date": "2021-01-03", 
                            "timeline": [
                                {
                                    "interval": "", 
                                    "no2_val": "28", 
                                    "pm10_val": "11", 
                                    "time": "600", 
                                    "valid": "2021-01-03T09:00:00+00:00"
                                }
                            ]
                        }
                    ], 
                    "id": "E25_", 
                    "parentId": "", 
                    "title": "Nova Gorica"
                }, 
                "type": "Feature"
            }
        ], 
        "icon_format": "png", 
        "icon_url_base": "http://www.meteo.si/uploads/meteo/style/img/weather/", 
        "language": "sl", 
        "params": {
            "no2_val": {
                "desc": "Du\u0161ikov dioksid", 
                "name": "NO2", 
                "unit": "\u03bcg/m\u00b3"
            }, 
            "pm10_val": {
                "desc": "Delci PM10", 
                "name": "PM10", 
                "unit": "\u03bcg/m\u00b3"
            }
        }, 
        "tsUpdated": "2021-01-03T09:12:01+00:00", 
        "type": "FeatureCollection", 
        "webcamUrl": "http://www.meteo.si/uploads/probase/www/observ/webcam/"
    }, 
    "observation_si_water": {
        "dataType": "observationAms", 
        "features": [
            {
                "geometry": {
                    "coordinates": [
                        13.865, 
                        46.279000000000003
                    ], 
                    "type": "Point"
                }, 
                "properties": {
                    "country": "SI", 
                    "days": [
                        {
                            "UTCoffset": "+01:00", 
                            "date": "2021-01-03", 
                            "timeline": [
                                {
                                    "time": "600", 
                                    "tw": "5", 
                                    "valid": "2021-01-03T09:00:00+00:00", 
                                    "wLev": "30"
                                }
                            ]
                        }
                    ], 
                    "id": "HYDRO-3280", 
                    "title": "Bohinjsko jezero"
                }, 
                "type": "Feature"
            }, 
            {
                "geometry": {
                    "coordinates": [
                        14.099, 
                        46.359999999999999
                    ], 
                    "type": "Point"
                }, 
                "properties": {
                    "country": "SI", 
                    "days": [
                        {
                            "UTCoffset": "+01:00", 
                            "date": "2021-01-03", 
                            "timeline": [
                                {
                                    "time": "600", 
                                    "tw": "6", 
                                    "valid": "2021-01-03T09:00:00+00:00", 
                                    "wLev": "50"
                                }
                            ]
                        }
                    ], 
                    "id": "HYDRO-3350", 
                    "title": "Blejsko jezero"
                }, 
                "type": "Feature"
            }, 
            {
                "geometry": {
                    "coordinates": [
                        15.076000000000001, 
                        45.484999999999999
                    ], 
                    "type": "Point"
                }, 
                "properties": {
                    "country": "SI", 
                    "days": [
                        {
                            "UTCoffset": "+01:00", 
                            "date": "2021-01-03", 
                            "timeline": [
                                {
                                    "time": "600", 
                                    "tw": "8", 
                                    "valid": "2021-01-03T09:00:00+00:00", 
                                    "wLev": "183"
                                }
                            ]
                        }
                    ], 
                    "id": "HYDRO-4828", 
                    "title": "Kolpa"
                }, 
                "type": "Feature"
            }, 
            {
                "geometry": {
                    "coordinates": [
                        13.724, 
                        45.548000000000002
                    ], 
                    "type": "Point"
                }, 
                "properties": {
                    "country": "SI", 
                    "days": [
                        {
                            "UTCoffset": "+01:00", 
                            "date": "2021-01-03", 
                            "timeline": [
                                {
                                    "time": "600", 
                                    "tw": "13", 
                                    "valid": "2021-01-03T09:00:00+00:00", 
                                    "wLev": "267"
                                }
                            ]
                        }
                    ], 
                    "id": "HYDRO-9350", 
                    "title": "Jadransko morje"
                }, 
                "type": "Feature"
            }
        ], 
        "icon_format": "png", 
        "icon_url_base": "http://www.meteo.si/uploads/meteo/style/img/weather/", 
        "language": "sl", 
        "params": {
            "tw": {
                "desc": "Temp. vode", 
                "unit": "\u00b0C"
            }, 
            "wLev": {
                "desc": "Vodostaj", 
                "unit": "cm"
            }
        }, 
        "type": "FeatureCollection"
    }, 
    "warning_si": {
        "icon_url_base": "http://www.meteo.si/uploads/meteo/style/img/warning/", 
        "language": "sl", 
        "locations": [
            {
                "countryIsoCode2": "SI", 
                "id": "SLOVENIA_", 
                "name": "Slovenija", 
                "summary": [
                    {
                        "event": [
                            {
                                "degree": "orange", 
                                "parameter": "WarningAvalanche", 
                                "parameter_desc": "Sne\u017eni plazovi", 
                                "region_map": "warning_avalanche_si-region_d1hlast-d3h00.png", 
                                "validEnd": "2021-01-04T11:59:00+00:00", 
                                "validStart": "2021-01-03T08:00:00+00:00"
                            }
                        ], 
                        "interval": "2 days", 
                        "type": "maxDegreeEvent"
                    }, 
                    {
                        "event": [
                            {
                                "degree": "orange", 
                                "parameter": "WarningAvalanche", 
                                "parameter_desc": "Sne\u017eni plazovi", 
                                "validEnd": "2021-01-04T11:59:00+00:00", 
                                "validStart": "2021-01-03T08:00:00+00:00"
                            }
                        ], 
                        "interval": "5 days", 
                        "type": "maxDegreeEvent"
                    }
                ], 
                "text": {
                    "id": "warning_SLOVENIA", 
                    "para": [
                        "Predvsem v visokogorju Julijskih Alp je velika nevarnost sne\u017enih plazov."
                    ], 
                    "title": "Opozorilo"
                }
            }
        ], 
        "map_url_base": "http://www.meteo.si//uploads/probase/www/warning/graphic/bundle/", 
        "type": "warning", 
        "updated": "2021-01-03T09:38:00+00:00"
    }
}