{
    "fcast_si_hint": {
        "articleinfo": {
            "pubdate": "Wednesday, 17.11.2021 ob 7h", 
            "title": "Vremenski namig", 
            "tsValid_issued": "2021-11-17 07:00"
        }, 
        "section": [
            {
                "id": "fcast_SLOVENIA_d1", 
                "para": [
                    {
                        "para": "Sve\u017ea epizoda #ARSOpodcast o ciklonih. Vabljeni k poslu\u0161anju! \ud83d\udd0a https://t.co/BT7s1C70uj https://t.co/ou0I50F6e2"
                    }
                ], 
                "title": "Zadnja novica"
            }
        ]
    }, 
    "fcast_si_text": {
        "articleinfo": {
            "pubdate": "Sreda, 17.11.2021 ob 9h", 
            "title": "Vremenska napoved", 
            "tsValid_issued": "2021-11-17 08:58"
        }, 
        "dataType": "", 
        "features": "", 
        "params": "", 
        "section": [
            {
                "para": "Danes bo prete\u017eno obla\u010dno, predvsem v ju\u017eni in zahodni Sloveniji bodo manj\u0161e krajevne plohe. Burja na Primorskem bo \u010dez dan prehodno ponehala. Najvi\u0161je dnevne temperature bodo od 6 do 11, na Primorskem do 15 \u00b0C.", 
                "title": "NAPOVED ZA SLOVENIJO"
            }, 
            {
                "para": "Jutri bo sprva prete\u017eno obla\u010dno z manj\u0161imi krajevnimi padavinami, ki bodo popoldne povsod ponehale, ponekod se bo obla\u010dnost trgala. Na Primorskem bo spet zapihala \u0161ibka burja. Jutranje temperature bodo od 2 do 6, na Primorskem do 10, najvi\u0161je dnevne od 6 do 10, na Primorskem do 15 \u00b0C.", 
                "title": "NAPOVED ZA SLOVENIJO"
            }, 
            {
                "para": "Danes bo obla\u010dno, predvsem ob severnem Jadranu in nad Furlanijo - Julijsko krajino bodo ob\u010dasno krajevne padavine, deloma plohe. Burja ob severnem Jadranu bo \u010dez dan ponehala.", 
                "title": "NAPOVED ZA SOSEDNJE POKRAJINE"
            }, 
            {
                "para": "Jutri bo sprva obla\u010dno, predvsem v krajih ju\u017eno od nas bodo ob\u010dasno rahle padavine, popoldne se bodo oblaki trgali. Ob severnem Jadranu bo spet zapihala \u0161ibka burja.", 
                "title": "NAPOVED ZA SOSEDNJE POKRAJINE"
            }, 
            {
                "para": "Nad osrednjim Sredozemljem \u0161e vztraja ciklonsko obmo\u010dje, severno od Alp pa se proti vzhodu pomika oslabljena vremenska fronta. Z vetrovi ju\u017enih smeri priteka k nam vla\u017een in razmeroma topel zrak.", 
                "title": "VREMENSKA SLIKA"
            }, 
            {
                "title": "VREMENSKA SLIKA"
            }, 
            {
                "para": "V petek in soboto bo prete\u017eno jasno, zjutraj in dopoldne bo po nekaterih ni\u017einah megla, ki se ponekod lahko zadr\u017ei ve\u010dji del dneva.", 
                "title": "OBETI"
            }, 
            {
                "para": "Dodatnega opozorila ni.", 
                "title": "OPOZORILO"
            }, 
            {
                "para": "Danes in jutri bo obla\u010dno s kak\u0161no kapljo de\u017eja, jutri popoldne se bo obla\u010dnost trgala. Na Primorskem bo pihala \u0161ibka burja.", 
                "title": "NAPOVED ZA SLOVENIJO - povzetek"
            }
        ], 
        "tsUpdated": "2021-11-17T07:58:59+00:00", 
        "type": "FeatureCollection"
    }, 
    "observation_si_avio": {
        "dataType": "observation", 
        "features": [
            {
                "geometry": {
                    "coordinates": [
                        15.525, 
                        45.893599999999999
                    ], 
                    "type": "Point"
                }, 
                "properties": {
                    "altitude": "154.0", 
                    "country": "SI", 
                    "days": [
                        {
                            "UTCoffset": "+01:00", 
                            "date": "2021-11-17", 
                            "timeline": [
                                {
                                    "clouds_icon_wwsyn_icon": "overcast_modFG_day", 
                                    "interval": "", 
                                    "time": "480", 
                                    "valid": "2021-11-17T07:00:00+00:00", 
                                    "vis_shortText": "<1", 
                                    "wwsyn_icon": "modFG"
                                }
                            ]
                        }
                    ], 
                    "id": "CERKLJE_LETAL-SCE_", 
                    "parentId": "SI_SPODNJEPOSAVSKA_", 
                    "title": "Letali\u0161\u010de Cerklje ob Krki"
                }, 
                "type": "Feature"
            }, 
            {
                "geometry": {
                    "coordinates": [
                        15.6869, 
                        46.479999999999997
                    ], 
                    "type": "Point"
                }, 
                "properties": {
                    "altitude": "264.0", 
                    "country": "SI", 
                    "days": [
                        {
                            "UTCoffset": "+01:00", 
                            "date": "2021-11-17", 
                            "timeline": [
                                {
                                    "clouds_icon_wwsyn_icon": "overcast_lightFG_day", 
                                    "interval": "", 
                                    "time": "480", 
                                    "valid": "2021-11-17T07:00:00+00:00", 
                                    "vis_shortText": "1-5", 
                                    "wwsyn_icon": "lightFG"
                                }
                            ]
                        }
                    ], 
                    "id": "MARIBOR_SLIVNICA_", 
                    "parentId": "SI_PODRAVSKA_", 
                    "title": "Letali\u0161\u010de Edvarda Rusjana Maribor"
                }, 
                "type": "Feature"
            }, 
            {
                "geometry": {
                    "coordinates": [
                        14.477499999999999, 
                        46.217799999999997
                    ], 
                    "type": "Point"
                }, 
                "properties": {
                    "altitude": "364.0", 
                    "country": "SI", 
                    "days": [
                        {
                            "UTCoffset": "+01:00", 
                            "date": "2021-11-17", 
                            "timeline": [
                                {
                                    "clouds_icon_wwsyn_icon": "overcast_lightFG_day", 
                                    "interval": "", 
                                    "time": "480", 
                                    "valid": "2021-11-17T07:00:00+00:00", 
                                    "vis_shortText": "1-5", 
                                    "wwsyn_icon": "lightFG"
                                }
                            ]
                        }
                    ], 
                    "id": "LJUBL-ANA_BRNIK_", 
                    "parentId": "SI_GORENJSKA_", 
                    "title": "Letali\u0161\u010de Jo\u017eeta Pu\u010dnika Ljubljana"
                }, 
                "type": "Feature"
            }, 
            {
                "geometry": {
                    "coordinates": [
                        13.6206, 
                        45.4756
                    ], 
                    "type": "Point"
                }, 
                "properties": {
                    "altitude": "2.0", 
                    "country": "SI", 
                    "days": [
                        {
                            "UTCoffset": "+01:00", 
                            "date": "2021-11-17", 
                            "timeline": [
                                {
                                    "clouds_icon_wwsyn_icon": "overcast_day", 
                                    "interval": "", 
                                    "time": "480", 
                                    "valid": "2021-11-17T07:00:00+00:00", 
                                    "vis_shortText": ">10", 
                                    "wwsyn_icon": ""
                                }
                            ]
                        }
                    ], 
                    "id": "PORTOROZ_SECOVLJE_", 
                    "parentId": "SI_OBALNO-KRASKA_", 
                    "title": "Letali\u0161\u010de Portoro\u017e"
                }, 
                "type": "Feature"
            }
        ], 
        "icon_base_url": "https://vreme.arso.gov.si/app/common/images/svg/weather/", 
        "icon_format": "png", 
        "language": "sl", 
        "params": {
            "clouds_icon_wwsyn_icon": {
                "desc": "Obla\u010dnost / Pojavi", 
                "name": "NPHENOM.", 
                "unit": ""
            }, 
            "vis_shortText": {
                "desc": "Vidnost", 
                "name": "VIS", 
                "unit": "km"
            }, 
            "wwsyn_icon": {
                "desc": "Pojavi", 
                "name": "PHENOM.", 
                "unit": ""
            }
        }, 
        "tsUpdated": "2021-11-17T07:13:04+00:00", 
        "type": "FeatureCollection", 
        "webcamUrl": "https://meteo.arso.gov.si/uploads/probase/www/observ/webcam/"
    }, 
    "observation_si_eco": {
        "dataType": "observationAms", 
        "features": [
            {
                "geometry": {
                    "coordinates": [
                        15.2257, 
                        46.236499999999999
                    ], 
                    "type": "Point"
                }, 
                "properties": {
                    "altitude": "244.0", 
                    "country": "SI", 
                    "days": [
                        {
                            "UTCoffset": "+01:00", 
                            "date": "2021-11-17", 
                            "timeline": [
                                {
                                    "interval": "", 
                                    "no2_val": "28", 
                                    "pm10_val": "68", 
                                    "time": "480", 
                                    "valid": "2021-11-17T07:00:00+00:00"
                                }
                            ]
                        }
                    ], 
                    "id": "METEO-1025_", 
                    "parentId": "SI_SAVINJSKA_", 
                    "title": "Celje"
                }, 
                "type": "Feature"
            }, 
            {
                "geometry": {
                    "coordinates": [
                        14.5124, 
                        46.0655
                    ], 
                    "type": "Point"
                }, 
                "properties": {
                    "altitude": "299.0", 
                    "country": "SI", 
                    "days": [
                        {
                            "UTCoffset": "+01:00", 
                            "date": "2021-11-17", 
                            "timeline": [
                                {
                                    "interval": "", 
                                    "no2_val": "34", 
                                    "pm10_val": "44", 
                                    "time": "480", 
                                    "valid": "2021-11-17T07:00:00+00:00"
                                }
                            ]
                        }
                    ], 
                    "id": "METEO-1495_", 
                    "parentId": "SI_OSREDNJESLOVENSKA_", 
                    "title": "Ljubljana"
                }, 
                "type": "Feature"
            }, 
            {
                "geometry": {
                    "coordinates": [
                        16.191299999999998, 
                        46.652099999999997
                    ], 
                    "type": "Point"
                }, 
                "properties": {
                    "altitude": "188.0", 
                    "country": "SI", 
                    "days": [
                        {
                            "UTCoffset": "+01:00", 
                            "date": "2021-11-17", 
                            "timeline": [
                                {
                                    "interval": "", 
                                    "no2_val": "18", 
                                    "pm10_val": "63", 
                                    "time": "480", 
                                    "valid": "2021-11-17T07:00:00+00:00"
                                }
                            ]
                        }
                    ], 
                    "id": "METEO-1444_", 
                    "parentId": "SI_POMURSKA_", 
                    "title": "Murska Sobota"
                }, 
                "type": "Feature"
            }, 
            {
                "geometry": {
                    "coordinates": [
                        13.6524, 
                        45.955599999999997
                    ], 
                    "type": "Point"
                }, 
                "properties": {
                    "altitude": "113", 
                    "country": "SI", 
                    "days": [
                        {
                            "UTCoffset": "+01:00", 
                            "date": "2021-11-17", 
                            "timeline": [
                                {
                                    "interval": "", 
                                    "no2_val": "48", 
                                    "pm10_val": "25", 
                                    "time": "480", 
                                    "valid": "2021-11-17T07:00:00+00:00"
                                }
                            ]
                        }
                    ], 
                    "id": "E25_", 
                    "parentId": "", 
                    "title": "Nova Gorica"
                }, 
                "type": "Feature"
            }
        ], 
        "icon_base_url": "https://vreme.arso.gov.si/app/common/images/svg/weather/", 
        "icon_format": "png", 
        "language": "sl", 
        "params": {
            "no2_val": {
                "desc": "Du\u0161ikov dioksid", 
                "name": "NO2", 
                "unit": "\u03bcg/m\u00b3"
            }, 
            "pm10_val": {
                "desc": "Delci PM10", 
                "name": "PM10", 
                "unit": "\u03bcg/m\u00b3"
            }
        }, 
        "tsUpdated": "2021-11-17T07:12:01+00:00", 
        "type": "FeatureCollection", 
        "webcamUrl": "https://meteo.arso.gov.si/uploads/probase/www/observ/webcam/"
    }, 
    "observation_si_water": {
        "dataType": "observationAms", 
        "features": [
            {
                "geometry": {
                    "coordinates": [
                        46.279000000000003, 
                        13.865
                    ], 
                    "type": "Point"
                }, 
                "properties": {
                    "country": "SI", 
                    "days": [
                        {
                            "UTCoffset": "+01:00", 
                            "date": "2021-11-17", 
                            "timeline": [
                                {
                                    "time": "480", 
                                    "tw": "8", 
                                    "valid": "2021-11-17T07:00:00+00:00", 
                                    "wLev": "27"
                                }
                            ]
                        }
                    ], 
                    "id": "HYDRO-3280", 
                    "title": "Bohinjsko jezero"
                }, 
                "type": "Feature"
            }, 
            {
                "geometry": {
                    "coordinates": [
                        46.359999999999999, 
                        14.099
                    ], 
                    "type": "Point"
                }, 
                "properties": {
                    "country": "SI", 
                    "days": [
                        {
                            "UTCoffset": "+01:00", 
                            "date": "2021-11-17", 
                            "timeline": [
                                {
                                    "time": "480", 
                                    "tw": "11", 
                                    "valid": "2021-11-17T07:00:00+00:00", 
                                    "wLev": "46"
                                }
                            ]
                        }
                    ], 
                    "id": "HYDRO-3350", 
                    "title": "Blejsko jezero"
                }, 
                "type": "Feature"
            }, 
            {
                "geometry": {
                    "coordinates": [
                        45.634999999999998, 
                        15.323
                    ], 
                    "type": "Point"
                }, 
                "properties": {
                    "country": "SI", 
                    "days": [
                        {
                            "UTCoffset": "+01:00", 
                            "date": "2021-11-17", 
                            "timeline": [
                                {
                                    "time": "480", 
                                    "tw": "9", 
                                    "valid": "2021-11-17T07:00:00+00:00", 
                                    "wLev": "34"
                                }
                            ]
                        }
                    ], 
                    "id": "HYDRO-4860", 
                    "title": "Kolpa"
                }, 
                "type": "Feature"
            }, 
            {
                "geometry": {
                    "coordinates": [
                        45.548000000000002, 
                        13.724
                    ], 
                    "type": "Point"
                }, 
                "properties": {
                    "country": "SI", 
                    "days": [
                        {
                            "UTCoffset": "+01:00", 
                            "date": "2021-11-17", 
                            "timeline": [
                                {
                                    "time": "480", 
                                    "tw": "15", 
                                    "valid": "2021-11-17T07:00:00+00:00", 
                                    "wLev": "283"
                                }
                            ]
                        }
                    ], 
                    "id": "HYDRO-9350", 
                    "title": "Jadransko morje"
                }, 
                "type": "Feature"
            }
        ], 
        "icon_format": "png", 
        "icon_url_base": "http://www.meteo.si/uploads/meteo/style/img/weather/", 
        "language": "sl", 
        "params": {
            "tw": {
                "desc": "Temp. vode", 
                "unit": "\u00b0C"
            }, 
            "wLev": {
                "desc": "Vodostaj", 
                "unit": "cm"
            }
        }, 
        "type": "FeatureCollection"
    }, 
    "warning_si": {
        "icon_url_base": "https://meteo.arso.gov.si/uploads/meteo/style/img/warning/", 
        "language": "sl", 
        "locations": [
            {
                "countryIsoCode2": "SI", 
                "id": "SLOVENIA_", 
                "name": "Slovenija", 
                "summary": [
                    {
                        "event": "", 
                        "interval": "2 days", 
                        "type": "maxDegreeEvent"
                    }, 
                    {
                        "event": "", 
                        "interval": "5 days", 
                        "type": "maxDegreeEvent"
                    }
                ], 
                "text": {
                    "id": "warning_SLOVENIA", 
                    "para": [
                        "Dodatnega opozorila ni."
                    ], 
                    "title": "Opozorilo"
                }
            }
        ], 
        "map_url_base": "https://meteo.arso.gov.si//uploads/probase/www/warning/graphic/bundle/", 
        "type": "warning", 
        "updated": "2021-11-17T06:17:00+00:00"
    }
}