[
    {
        "DEPTH": "30", 
        "EMS_NUM": null, 
        "FELT": "0", 
        "GEOLOC": "10 km SZ od Karlovca (Hrva\u0161ka)", 
        "INTENZITETA": null, 
        "LAT": "45.54", 
        "LON": "15.45", 
        "MAG1": "1.9", 
        "NSTA": "13", 
        "OBJECTID": "792495", 
        "ORID": "2068930", 
        "ORIGTIME": "21-06-2021 22:17:11.42", 
        "REVISION": "0", 
        "TIME": "21.06.2021 22:17:11", 
        "VPIS": "2021-06-22 05:32:20", 
        "ZAZNALI": "0"
    }, 
    {
        "DEPTH": "0", 
        "EMS_NUM": null, 
        "FELT": "1", 
        "GEOLOC": "2 km J od Topol\u0161ice", 
        "INTENZITETA": null, 
        "LAT": "46.39", 
        "LON": "15.03", 
        "MAG1": "1", 
        "NSTA": "6", 
        "OBJECTID": "792455", 
        "ORID": "2068580", 
        "ORIGTIME": "21-06-2021 11:01:52.19", 
        "REVISION": "0", 
        "TIME": "21.06.2021 11:01:52", 
        "VPIS": "2021-06-21 13:22:07", 
        "ZAZNALI": "2"
    }, 
    {
        "DEPTH": "13", 
        "EMS_NUM": null, 
        "FELT": "0", 
        "GEOLOC": "3 km S od Ko\u010devja", 
        "INTENZITETA": null, 
        "LAT": "45.67", 
        "LON": "14.85", 
        "MAG1": ".8", 
        "NSTA": "8", 
        "OBJECTID": "792438", 
        "ORID": null, 
        "ORIGTIME": "20-06-2021 14:01:07.80", 
        "REVISION": "1", 
        "TIME": "20.06.2021 14:01:07", 
        "VPIS": "2021-06-21 12:10:38", 
        "ZAZNALI": "0"
    }, 
    {
        "DEPTH": "13", 
        "EMS_NUM": null, 
        "FELT": "0", 
        "GEOLOC": "3 km S od Ko\u010devja", 
        "INTENZITETA": null, 
        "LAT": "45.67", 
        "LON": "14.86", 
        "MAG1": ".8", 
        "NSTA": "9", 
        "OBJECTID": "792437", 
        "ORID": null, 
        "ORIGTIME": "20-06-2021 08:26:38.80", 
        "REVISION": "1", 
        "TIME": "20.06.2021 08:26:38", 
        "VPIS": "2021-06-21 12:10:35", 
        "ZAZNALI": "0"
    }, 
    {
        "DEPTH": "13", 
        "EMS_NUM": null, 
        "FELT": "0", 
        "GEOLOC": "3 km S od Ko\u010devja", 
        "INTENZITETA": null, 
        "LAT": "45.67", 
        "LON": "14.85", 
        "MAG1": ".9", 
        "NSTA": "7", 
        "OBJECTID": "792375", 
        "ORID": "2067636", 
        "ORIGTIME": "20-06-2021 07:36:42.40", 
        "REVISION": "1", 
        "TIME": "20.06.2021 07:36:42", 
        "VPIS": "2021-06-21 12:10:31", 
        "ZAZNALI": "0"
    }, 
    {
        "DEPTH": "0", 
        "EMS_NUM": null, 
        "FELT": "1", 
        "GEOLOC": "4 km JV od Topol\u0161ice", 
        "INTENZITETA": null, 
        "LAT": "46.39", 
        "LON": "15.07", 
        "MAG1": "1.4", 
        "NSTA": "8", 
        "OBJECTID": "792335", 
        "ORID": "2066482", 
        "ORIGTIME": "19-06-2021 00:32:50.30", 
        "REVISION": "1", 
        "TIME": "19.06.2021 00:32:50", 
        "VPIS": "2021-06-21 10:40:35", 
        "ZAZNALI": "1"
    }, 
    {
        "DEPTH": "8", 
        "EMS_NUM": null, 
        "FELT": "0", 
        "GEOLOC": "6 km V od Grosuplja", 
        "INTENZITETA": null, 
        "LAT": "45.96", 
        "LON": "14.74", 
        "MAG1": ".8", 
        "NSTA": "9", 
        "OBJECTID": "792255", 
        "ORID": "2065169", 
        "ORIGTIME": "18-06-2021 02:38:36.64", 
        "REVISION": "0", 
        "TIME": "18.06.2021 02:38:36", 
        "VPIS": "2021-06-18 17:53:03", 
        "ZAZNALI": "0"
    }, 
    {
        "DEPTH": "0", 
        "EMS_NUM": null, 
        "FELT": "0", 
        "GEOLOC": "3 km V od Topol\u0161ice", 
        "INTENZITETA": null, 
        "LAT": "46.41", 
        "LON": "15.06", 
        "MAG1": ".6", 
        "NSTA": "8", 
        "OBJECTID": "792235", 
        "ORID": "2065048", 
        "ORIGTIME": "18-06-2021 01:08:26.34", 
        "REVISION": "0", 
        "TIME": "18.06.2021 01:08:26", 
        "VPIS": "2021-06-18 03:09:33", 
        "ZAZNALI": "0"
    }, 
    {
        "DEPTH": "8", 
        "EMS_NUM": null, 
        "FELT": "0", 
        "GEOLOC": "5 km SZ od Mislinje", 
        "INTENZITETA": null, 
        "LAT": "46.48", 
        "LON": "15.15", 
        "MAG1": "1.3", 
        "NSTA": "7", 
        "OBJECTID": "792521", 
        "ORID": null, 
        "ORIGTIME": "17-06-2021 21:11:57.60", 
        "REVISION": "1", 
        "TIME": "17.06.2021 21:11:57", 
        "VPIS": "2021-06-22 08:57:25", 
        "ZAZNALI": "0"
    }, 
    {
        "DEPTH": "14", 
        "EMS_NUM": null, 
        "FELT": "0", 
        "GEOLOC": "15 km J od Babnega Polja", 
        "INTENZITETA": null, 
        "LAT": "45.52", 
        "LON": "14.48", 
        "MAG1": ".8", 
        "NSTA": "7", 
        "OBJECTID": "792520", 
        "ORID": null, 
        "ORIGTIME": "17-06-2021 18:18:39.90", 
        "REVISION": "1", 
        "TIME": "17.06.2021 18:18:39", 
        "VPIS": "2021-06-22 08:57:20", 
        "ZAZNALI": "0"
    }, 
    {
        "DEPTH": "10", 
        "EMS_NUM": null, 
        "FELT": "0", 
        "GEOLOC": "2 km Z od Trojan", 
        "INTENZITETA": null, 
        "LAT": "46.19", 
        "LON": "14.86", 
        "MAG1": ".2", 
        "NSTA": "11", 
        "OBJECTID": "792200", 
        "ORID": null, 
        "ORIGTIME": "16-06-2021 22:06:50.40", 
        "REVISION": "1", 
        "TIME": "16.06.2021 22:06:50", 
        "VPIS": "2021-06-17 12:57:28", 
        "ZAZNALI": "0"
    }, 
    {
        "DEPTH": "12", 
        "EMS_NUM": null, 
        "FELT": "1", 
        "GEOLOC": "12 km J od Obre\u017eja", 
        "INTENZITETA": null, 
        "LAT": "45.74", 
        "LON": "15.73", 
        "MAG1": "2", 
        "NSTA": "34", 
        "OBJECTID": "792155", 
        "ORID": "2063615", 
        "ORIGTIME": "16-06-2021 15:28:48.50", 
        "REVISION": "1", 
        "TIME": "16.06.2021 15:28:48", 
        "VPIS": "2021-06-17 12:57:22", 
        "ZAZNALI": "1"
    }, 
    {
        "DEPTH": "15", 
        "EMS_NUM": null, 
        "FELT": "0", 
        "GEOLOC": "15 km V od Jel\u0161an", 
        "INTENZITETA": null, 
        "LAT": "45.5", 
        "LON": "14.47", 
        "MAG1": "1", 
        "NSTA": "6", 
        "OBJECTID": "792199", 
        "ORID": null, 
        "ORIGTIME": "16-06-2021 14:28:30.60", 
        "REVISION": "1", 
        "TIME": "16.06.2021 14:28:30", 
        "VPIS": "2021-06-17 12:57:17", 
        "ZAZNALI": "0"
    }, 
    {
        "DEPTH": "13", 
        "EMS_NUM": null, 
        "FELT": "0", 
        "GEOLOC": "16 km V od Jel\u0161an", 
        "INTENZITETA": null, 
        "LAT": "45.5", 
        "LON": "14.48", 
        "MAG1": "1", 
        "NSTA": "4", 
        "OBJECTID": "792198", 
        "ORID": null, 
        "ORIGTIME": "16-06-2021 10:40:29.50", 
        "REVISION": "1", 
        "TIME": "16.06.2021 10:40:29", 
        "VPIS": "2021-06-17 12:57:11", 
        "ZAZNALI": "0"
    }, 
    {
        "DEPTH": "15", 
        "EMS_NUM": null, 
        "FELT": "0", 
        "GEOLOC": "16 km J od Babnega Polja", 
        "INTENZITETA": null, 
        "LAT": "45.51", 
        "LON": "14.48", 
        "MAG1": "1.2", 
        "NSTA": "12", 
        "OBJECTID": "792196", 
        "ORID": null, 
        "ORIGTIME": "16-06-2021 04:09:57.10", 
        "REVISION": "1", 
        "TIME": "16.06.2021 04:09:57", 
        "VPIS": "2021-06-17 12:57:06", 
        "ZAZNALI": "0"
    }, 
    {
        "DEPTH": "10", 
        "EMS_NUM": null, 
        "FELT": "1", 
        "GEOLOC": "7 km SV od Ilirske Bistrice", 
        "INTENZITETA": null, 
        "LAT": "45.61", 
        "LON": "14.33", 
        "MAG1": "1.6", 
        "NSTA": "20", 
        "OBJECTID": "792035", 
        "ORID": "2062851", 
        "ORIGTIME": "16-06-2021 03:16:51.50", 
        "REVISION": "1", 
        "TIME": "16.06.2021 03:16:51", 
        "VPIS": "2021-06-17 12:57:02", 
        "ZAZNALI": "1"
    }, 
    {
        "DEPTH": "15", 
        "EMS_NUM": null, 
        "FELT": "0", 
        "GEOLOC": "16 km V od Jel\u0161an", 
        "INTENZITETA": null, 
        "LAT": "45.5", 
        "LON": "14.48", 
        "MAG1": "1.1", 
        "NSTA": "16", 
        "OBJECTID": "792015", 
        "ORID": "2062724", 
        "ORIGTIME": "15-06-2021 20:08:34.60", 
        "REVISION": "1", 
        "TIME": "15.06.2021 20:08:34", 
        "VPIS": "2021-06-16 14:04:57", 
        "ZAZNALI": "0"
    }, 
    {
        "DEPTH": "13", 
        "EMS_NUM": null, 
        "FELT": "0", 
        "GEOLOC": "9 km V od Pivke", 
        "INTENZITETA": null, 
        "LAT": "45.69", 
        "LON": "14.31", 
        "MAG1": ".9", 
        "NSTA": "6", 
        "OBJECTID": "792125", 
        "ORID": null, 
        "ORIGTIME": "15-06-2021 12:24:59.60", 
        "REVISION": "1", 
        "TIME": "15.06.2021 12:24:59", 
        "VPIS": "2021-06-16 14:04:47", 
        "ZAZNALI": "0"
    }, 
    {
        "DEPTH": "16", 
        "EMS_NUM": null, 
        "FELT": "0", 
        "GEOLOC": "16 km J od Babnega Polja", 
        "INTENZITETA": null, 
        "LAT": "45.51", 
        "LON": "14.49", 
        "MAG1": "2.2", 
        "NSTA": "41", 
        "OBJECTID": "791955", 
        "ORID": "2062029", 
        "ORIGTIME": "15-06-2021 11:02:30.50", 
        "REVISION": "1", 
        "TIME": "15.06.2021 11:02:30", 
        "VPIS": "2021-06-16 14:04:42", 
        "ZAZNALI": "0"
    }, 
    {
        "DEPTH": "15", 
        "EMS_NUM": null, 
        "FELT": "0", 
        "GEOLOC": "15 km V od Jel\u0161an", 
        "INTENZITETA": null, 
        "LAT": "45.5", 
        "LON": "14.47", 
        "MAG1": "1", 
        "NSTA": "6", 
        "OBJECTID": "792123", 
        "ORID": null, 
        "ORIGTIME": "15-06-2021 09:24:15.20", 
        "REVISION": "1", 
        "TIME": "15.06.2021 09:24:15", 
        "VPIS": "2021-06-16 14:04:37", 
        "ZAZNALI": "0"
    }, 
    {
        "DEPTH": "8", 
        "EMS_NUM": null, 
        "FELT": "0", 
        "GEOLOC": "6 km SZ od Hrastovelj", 
        "INTENZITETA": null, 
        "LAT": "45.55", 
        "LON": "13.85", 
        "MAG1": ".9", 
        "NSTA": "5", 
        "OBJECTID": "792122", 
        "ORID": null, 
        "ORIGTIME": "15-06-2021 08:37:13.40", 
        "REVISION": "1", 
        "TIME": "15.06.2021 08:37:13", 
        "VPIS": "2021-06-16 14:04:32", 
        "ZAZNALI": "0"
    }, 
    {
        "DEPTH": "14", 
        "EMS_NUM": null, 
        "FELT": "0", 
        "GEOLOC": "15 km J od Babnega Polja", 
        "INTENZITETA": null, 
        "LAT": "45.52", 
        "LON": "14.48", 
        "MAG1": "1.1", 
        "NSTA": "11", 
        "OBJECTID": "792121", 
        "ORID": null, 
        "ORIGTIME": "15-06-2021 08:10:08.80", 
        "REVISION": "1", 
        "TIME": "15.06.2021 08:10:08", 
        "VPIS": "2021-06-16 14:04:28", 
        "ZAZNALI": "0"
    }, 
    {
        "DEPTH": "14", 
        "EMS_NUM": null, 
        "FELT": "0", 
        "GEOLOC": "16 km V od Jel\u0161an", 
        "INTENZITETA": null, 
        "LAT": "45.5", 
        "LON": "14.48", 
        "MAG1": "1", 
        "NSTA": "10", 
        "OBJECTID": "792075", 
        "ORID": null, 
        "ORIGTIME": "14-06-2021 20:27:16.20", 
        "REVISION": "1", 
        "TIME": "14.06.2021 20:27:16", 
        "VPIS": "2021-06-16 11:25:46", 
        "ZAZNALI": "0"
    }, 
    {
        "DEPTH": "14", 
        "EMS_NUM": null, 
        "FELT": "0", 
        "GEOLOC": "16 km J od Babnega Polja", 
        "INTENZITETA": null, 
        "LAT": "45.51", 
        "LON": "14.48", 
        "MAG1": ".9", 
        "NSTA": "8", 
        "OBJECTID": "792060", 
        "ORID": null, 
        "ORIGTIME": "14-06-2021 16:55:19.10", 
        "REVISION": "1", 
        "TIME": "14.06.2021 16:55:19", 
        "VPIS": "2021-06-16 11:25:41", 
        "ZAZNALI": "0"
    }, 
    {
        "DEPTH": "15", 
        "EMS_NUM": null, 
        "FELT": "0", 
        "GEOLOC": "16 km J od Babnega Polja", 
        "INTENZITETA": null, 
        "LAT": "45.51", 
        "LON": "14.48", 
        "MAG1": "1.8", 
        "NSTA": "20", 
        "OBJECTID": "791855", 
        "ORID": "2061281", 
        "ORIGTIME": "14-06-2021 14:32:26.50", 
        "REVISION": "1", 
        "TIME": "14.06.2021 14:32:26", 
        "VPIS": "2021-06-16 11:25:37", 
        "ZAZNALI": "0"
    }, 
    {
        "DEPTH": "15", 
        "EMS_NUM": null, 
        "FELT": "0", 
        "GEOLOC": "15 km V od Jel\u0161an", 
        "INTENZITETA": null, 
        "LAT": "45.5", 
        "LON": "14.47", 
        "MAG1": "1", 
        "NSTA": "7", 
        "OBJECTID": "792059", 
        "ORID": null, 
        "ORIGTIME": "14-06-2021 10:40:39.70", 
        "REVISION": "1", 
        "TIME": "14.06.2021 10:40:39", 
        "VPIS": "2021-06-16 11:25:32", 
        "ZAZNALI": "0"
    }, 
    {
        "DEPTH": "13", 
        "EMS_NUM": null, 
        "FELT": "0", 
        "GEOLOC": "16 km V od Jel\u0161an", 
        "INTENZITETA": null, 
        "LAT": "45.49", 
        "LON": "14.48", 
        "MAG1": ".9", 
        "NSTA": "5", 
        "OBJECTID": "792058", 
        "ORID": null, 
        "ORIGTIME": "14-06-2021 10:30:47.30", 
        "REVISION": "1", 
        "TIME": "14.06.2021 10:30:47", 
        "VPIS": "2021-06-16 11:25:27", 
        "ZAZNALI": "0"
    }, 
    {
        "DEPTH": "16", 
        "EMS_NUM": null, 
        "FELT": "0", 
        "GEOLOC": "6 km V od Trojan", 
        "INTENZITETA": null, 
        "LAT": "46.2", 
        "LON": "14.97", 
        "MAG1": ".4", 
        "NSTA": "9", 
        "OBJECTID": "792056", 
        "ORID": null, 
        "ORIGTIME": "14-06-2021 03:09:47.90", 
        "REVISION": "1", 
        "TIME": "14.06.2021 03:09:47", 
        "VPIS": "2021-06-16 11:25:14", 
        "ZAZNALI": "0"
    }, 
    {
        "DEPTH": "15", 
        "EMS_NUM": null, 
        "FELT": "0", 
        "GEOLOC": "16 km J od Babnega Polja", 
        "INTENZITETA": null, 
        "LAT": "45.51", 
        "LON": "14.48", 
        "MAG1": "1.1", 
        "NSTA": "11", 
        "OBJECTID": "792055", 
        "ORID": null, 
        "ORIGTIME": "14-06-2021 00:02:52.90", 
        "REVISION": "1", 
        "TIME": "14.06.2021 00:02:52", 
        "VPIS": "2021-06-16 11:25:09", 
        "ZAZNALI": "0"
    }, 
    {
        "DEPTH": "16", 
        "EMS_NUM": null, 
        "FELT": "0", 
        "GEOLOC": "16 km V od Jel\u0161an", 
        "INTENZITETA": null, 
        "LAT": "45.5", 
        "LON": "14.48", 
        "MAG1": ".9", 
        "NSTA": "15", 
        "OBJECTID": "791715", 
        "ORID": "2059978", 
        "ORIGTIME": "12-06-2021 21:34:01.90", 
        "REVISION": "1", 
        "TIME": "12.06.2021 21:34:01", 
        "VPIS": "2021-06-16 15:41:03", 
        "ZAZNALI": "0"
    }, 
    {
        "DEPTH": "8", 
        "EMS_NUM": null, 
        "FELT": "0", 
        "GEOLOC": "7 km V od Ivan\u010dne Gorice", 
        "INTENZITETA": null, 
        "LAT": "45.93", 
        "LON": "14.9", 
        "MAG1": ".3", 
        "NSTA": "10", 
        "OBJECTID": "791695", 
        "ORID": "2059792", 
        "ORIGTIME": "11-06-2021 23:12:09.40", 
        "REVISION": "1", 
        "TIME": "11.06.2021 23:12:09", 
        "VPIS": "2021-06-15 12:44:08", 
        "ZAZNALI": "0"
    }, 
    {
        "DEPTH": "0", 
        "EMS_NUM": null, 
        "FELT": "4", 
        "GEOLOC": "4 km JV od Topol\u0161ice", 
        "INTENZITETA": null, 
        "LAT": "46.39", 
        "LON": "15.07", 
        "MAG1": "1.4", 
        "NSTA": "9", 
        "OBJECTID": "791655", 
        "ORID": "2059142", 
        "ORIGTIME": "11-06-2021 02:39:15.00", 
        "REVISION": "1", 
        "TIME": "11.06.2021 02:39:15", 
        "VPIS": "2021-06-17 07:27:55", 
        "ZAZNALI": "4"
    }, 
    {
        "DEPTH": "0", 
        "EMS_NUM": null, 
        "FELT": "4", 
        "GEOLOC": "4 km JV od Topol\u0161ice", 
        "INTENZITETA": null, 
        "LAT": "46.39", 
        "LON": "15.07", 
        "MAG1": ".7", 
        "NSTA": "7", 
        "OBJECTID": "791635", 
        "ORID": "2059053", 
        "ORIGTIME": "11-06-2021 02:38:31.40", 
        "REVISION": "1", 
        "TIME": "11.06.2021 02:38:31", 
        "VPIS": "2021-06-17 07:27:55", 
        "ZAZNALI": "1"
    }, 
    {
        "DEPTH": "5", 
        "EMS_NUM": null, 
        "FELT": "0", 
        "GEOLOC": "10 km J od Zagorja ob Savi", 
        "INTENZITETA": null, 
        "LAT": "46.02", 
        "LON": "15", 
        "MAG1": ".1", 
        "NSTA": "11", 
        "OBJECTID": "791937", 
        "ORID": null, 
        "ORIGTIME": "11-06-2021 02:02:07.60", 
        "REVISION": "1", 
        "TIME": "11.06.2021 02:02:07", 
        "VPIS": "2021-06-15 12:43:40", 
        "ZAZNALI": "0"
    }, 
    {
        "DEPTH": "5", 
        "EMS_NUM": null, 
        "FELT": "0", 
        "GEOLOC": "10 km J od Zagorja ob Savi", 
        "INTENZITETA": null, 
        "LAT": "46.02", 
        "LON": "14.99", 
        "MAG1": ".3", 
        "NSTA": "12", 
        "OBJECTID": "791936", 
        "ORID": null, 
        "ORIGTIME": "11-06-2021 01:33:45.90", 
        "REVISION": "1", 
        "TIME": "11.06.2021 01:33:45", 
        "VPIS": "2021-06-15 12:43:35", 
        "ZAZNALI": "0"
    }, 
    {
        "DEPTH": "6", 
        "EMS_NUM": null, 
        "FELT": "1", 
        "GEOLOC": "10 km J od Zagorja ob Savi", 
        "INTENZITETA": null, 
        "LAT": "46.02", 
        "LON": "15", 
        "MAG1": ".9", 
        "NSTA": "27", 
        "OBJECTID": "791615", 
        "ORID": "2058878", 
        "ORIGTIME": "11-06-2021 01:26:26.50", 
        "REVISION": "1", 
        "TIME": "11.06.2021 01:26:26", 
        "VPIS": "2021-06-15 12:43:29", 
        "ZAZNALI": "1"
    }, 
    {
        "DEPTH": "10", 
        "EMS_NUM": null, 
        "FELT": "0", 
        "GEOLOC": "7 km V od Jel\u0161an", 
        "INTENZITETA": null, 
        "LAT": "45.52", 
        "LON": "14.36", 
        "MAG1": ".8", 
        "NSTA": "6", 
        "OBJECTID": "791797", 
        "ORID": null, 
        "ORIGTIME": "10-06-2021 05:35:11.90", 
        "REVISION": "1", 
        "TIME": "10.06.2021 05:35:11", 
        "VPIS": "2021-06-14 03:39:10", 
        "ZAZNALI": "0"
    }, 
    {
        "DEPTH": "9", 
        "EMS_NUM": null, 
        "FELT": "1", 
        "GEOLOC": "22 km JV od \u0160ibenika (Hrva\u0161ka)", 
        "INTENZITETA": null, 
        "LAT": "43.62", 
        "LON": "16.11", 
        "MAG1": "4.3", 
        "NSTA": "9", 
        "OBJECTID": "791295", 
        "ORID": "2055733", 
        "ORIGTIME": "08-06-2021 03:59:52.40", 
        "REVISION": "2", 
        "TIME": "08.06.2021 03:59:52", 
        "VPIS": "2021-06-11 10:44:20", 
        "ZAZNALI": "3"
    }, 
    {
        "DEPTH": "11", 
        "EMS_NUM": null, 
        "FELT": "0", 
        "GEOLOC": "1 km V od Pivke", 
        "INTENZITETA": null, 
        "LAT": "45.68", 
        "LON": "14.21", 
        "MAG1": ".5", 
        "NSTA": "13", 
        "OBJECTID": "791340", 
        "ORID": null, 
        "ORIGTIME": "07-06-2021 17:24:26.20", 
        "REVISION": "1", 
        "TIME": "07.06.2021 17:24:26", 
        "VPIS": "2021-06-08 11:15:36", 
        "ZAZNALI": "0"
    }, 
    {
        "DEPTH": "9", 
        "EMS_NUM": null, 
        "FELT": "0", 
        "GEOLOC": "2 km V od Grosuplja", 
        "INTENZITETA": null, 
        "LAT": "45.95", 
        "LON": "14.69", 
        "MAG1": ".5", 
        "NSTA": "18", 
        "OBJECTID": "791175", 
        "ORID": "2054918", 
        "ORIGTIME": "07-06-2021 01:05:19.50", 
        "REVISION": "1", 
        "TIME": "07.06.2021 01:05:19", 
        "VPIS": "2021-06-08 11:15:12", 
        "ZAZNALI": "0"
    }, 
    {
        "DEPTH": "6", 
        "EMS_NUM": null, 
        "FELT": "0", 
        "GEOLOC": "3 km JV od Mislinje", 
        "INTENZITETA": null, 
        "LAT": "46.42", 
        "LON": "15.22", 
        "MAG1": ".8", 
        "NSTA": "11", 
        "OBJECTID": "791135", 
        "ORID": "2054233", 
        "ORIGTIME": "06-06-2021 13:49:13.30", 
        "REVISION": "1", 
        "TIME": "06.06.2021 13:49:13", 
        "VPIS": "2021-06-08 15:15:56", 
        "ZAZNALI": "0"
    }, 
    {
        "DEPTH": "0", 
        "EMS_NUM": null, 
        "FELT": "1", 
        "GEOLOC": "4 km JV od Topol\u0161ice", 
        "INTENZITETA": null, 
        "LAT": "46.39", 
        "LON": "15.07", 
        "MAG1": "1.6", 
        "NSTA": "4", 
        "OBJECTID": "791075", 
        "ORID": "2053609", 
        "ORIGTIME": "06-06-2021 08:43:27.10", 
        "REVISION": "1", 
        "TIME": "06.06.2021 08:43:27", 
        "VPIS": "2021-06-08 15:15:45", 
        "ZAZNALI": "17"
    }, 
    {
        "DEPTH": "13", 
        "EMS_NUM": null, 
        "FELT": "0", 
        "GEOLOC": "15 km J od Babnega Polja", 
        "INTENZITETA": null, 
        "LAT": "45.52", 
        "LON": "14.48", 
        "MAG1": "1.1", 
        "NSTA": "21", 
        "OBJECTID": "791055", 
        "ORID": "2053582", 
        "ORIGTIME": "06-06-2021 07:04:48.30", 
        "REVISION": "1", 
        "TIME": "06.06.2021 07:04:48", 
        "VPIS": "2021-06-08 15:15:39", 
        "ZAZNALI": "0"
    }, 
    {
        "DEPTH": "4", 
        "EMS_NUM": null, 
        "FELT": "0", 
        "GEOLOC": "7 km JZ od \u0160kofje Loke", 
        "INTENZITETA": null, 
        "LAT": "46.13", 
        "LON": "14.24", 
        "MAG1": ".3", 
        "NSTA": "11", 
        "OBJECTID": "791356", 
        "ORID": null, 
        "ORIGTIME": "06-06-2021 05:55:23.70", 
        "REVISION": "1", 
        "TIME": "06.06.2021 05:55:23", 
        "VPIS": "2021-06-08 15:15:33", 
        "ZAZNALI": "0"
    }, 
    {
        "DEPTH": "11", 
        "EMS_NUM": null, 
        "FELT": "0", 
        "GEOLOC": "5 km SZ od Trebnjega", 
        "INTENZITETA": null, 
        "LAT": "45.94", 
        "LON": "14.96", 
        "MAG1": ".8", 
        "NSTA": "8", 
        "OBJECTID": "791015", 
        "ORID": "2053237", 
        "ORIGTIME": "05-06-2021 09:49:21.20", 
        "REVISION": "1", 
        "TIME": "05.06.2021 09:49:21", 
        "VPIS": "2021-06-07 14:30:56", 
        "ZAZNALI": "0"
    }, 
    {
        "DEPTH": "6", 
        "EMS_NUM": null, 
        "FELT": "1", 
        "GEOLOC": "7 km J od Hrastovelj", 
        "INTENZITETA": null, 
        "LAT": "45.45", 
        "LON": "13.88", 
        "MAG1": ".8", 
        "NSTA": "12", 
        "OBJECTID": "790995", 
        "ORID": "2053154", 
        "ORIGTIME": "05-06-2021 03:36:36.70", 
        "REVISION": "1", 
        "TIME": "05.06.2021 03:36:36", 
        "VPIS": "2021-06-10 10:44:48", 
        "ZAZNALI": "1"
    }, 
    {
        "DEPTH": "5", 
        "EMS_NUM": null, 
        "FELT": "0", 
        "GEOLOC": "9 km J od \u010cepovana", 
        "INTENZITETA": null, 
        "LAT": "45.97", 
        "LON": "13.81", 
        "MAG1": "-.3", 
        "NSTA": "9", 
        "OBJECTID": "791222", 
        "ORID": null, 
        "ORIGTIME": "04-06-2021 23:18:50.00", 
        "REVISION": "1", 
        "TIME": "04.06.2021 23:18:50", 
        "VPIS": "2021-06-07 10:15:03", 
        "ZAZNALI": "0"
    }, 
    {
        "DEPTH": "5", 
        "EMS_NUM": null, 
        "FELT": "0", 
        "GEOLOC": "7 km SV od Litije", 
        "INTENZITETA": null, 
        "LAT": "46.11", 
        "LON": "14.87", 
        "MAG1": ".6", 
        "NSTA": "10", 
        "OBJECTID": "791220", 
        "ORID": null, 
        "ORIGTIME": "04-06-2021 17:50:17.80", 
        "REVISION": "1", 
        "TIME": "04.06.2021 17:50:17", 
        "VPIS": "2021-06-07 10:14:55", 
        "ZAZNALI": "0"
    }, 
    {
        "DEPTH": "9", 
        "EMS_NUM": null, 
        "FELT": "0", 
        "GEOLOC": "2 km SZ od Rade\u010d", 
        "INTENZITETA": null, 
        "LAT": "46.08", 
        "LON": "15.18", 
        "MAG1": ".1", 
        "NSTA": "10", 
        "OBJECTID": "791217", 
        "ORID": null, 
        "ORIGTIME": "04-06-2021 01:28:47.60", 
        "REVISION": "1", 
        "TIME": "04.06.2021 01:28:47", 
        "VPIS": "2021-06-07 10:14:43", 
        "ZAZNALI": "0"
    }, 
    {
        "DEPTH": "12", 
        "EMS_NUM": null, 
        "FELT": "1", 
        "GEOLOC": "3 km S od Rade\u010d", 
        "INTENZITETA": null, 
        "LAT": "46.09", 
        "LON": "15.18", 
        "MAG1": "1.7", 
        "NSTA": "30", 
        "OBJECTID": "790835", 
        "ORID": "2051228", 
        "ORIGTIME": "03-06-2021 16:03:12.30", 
        "REVISION": "1", 
        "TIME": "03.06.2021 16:03:12", 
        "VPIS": "2021-06-04 13:33:33", 
        "ZAZNALI": "4"
    }, 
    {
        "DEPTH": "5", 
        "EMS_NUM": null, 
        "FELT": "0", 
        "GEOLOC": "7 km SV od Litije", 
        "INTENZITETA": null, 
        "LAT": "46.11", 
        "LON": "14.87", 
        "MAG1": ".9", 
        "NSTA": "10", 
        "OBJECTID": "790755", 
        "ORID": "2050376", 
        "ORIGTIME": "03-06-2021 04:18:31.00", 
        "REVISION": "1", 
        "TIME": "03.06.2021 04:18:31", 
        "VPIS": "2021-06-04 13:33:29", 
        "ZAZNALI": "0"
    }, 
    {
        "DEPTH": "0", 
        "EMS_NUM": null, 
        "FELT": "1", 
        "GEOLOC": "4 km JV od Topol\u0161ice", 
        "INTENZITETA": null, 
        "LAT": "46.39", 
        "LON": "15.07", 
        "MAG1": ".6", 
        "NSTA": "5", 
        "OBJECTID": "790735", 
        "ORID": "2050176", 
        "ORIGTIME": "03-06-2021 01:43:33.10", 
        "REVISION": "1", 
        "TIME": "03.06.2021 01:43:33", 
        "VPIS": "2021-06-04 13:33:23", 
        "ZAZNALI": "1"
    }, 
    {
        "DEPTH": "8", 
        "EMS_NUM": null, 
        "FELT": "1", 
        "GEOLOC": "6 km SZ od Novega mesta", 
        "INTENZITETA": null, 
        "LAT": "45.83", 
        "LON": "15.12", 
        "MAG1": "1", 
        "NSTA": "17", 
        "OBJECTID": "790635", 
        "ORID": "2049091", 
        "ORIGTIME": "02-06-2021 09:35:30.00", 
        "REVISION": "1", 
        "TIME": "02.06.2021 09:35:30", 
        "VPIS": "2021-06-03 15:38:16", 
        "ZAZNALI": "1"
    }, 
    {
        "DEPTH": "11", 
        "EMS_NUM": null, 
        "FELT": "1", 
        "GEOLOC": "6 km V od Ivan\u010dne Gorice", 
        "INTENZITETA": null, 
        "LAT": "45.94", 
        "LON": "14.88", 
        "MAG1": ".7", 
        "NSTA": "20", 
        "OBJECTID": "790615", 
        "ORID": "2048767", 
        "ORIGTIME": "01-06-2021 23:50:41.80", 
        "REVISION": "1", 
        "TIME": "01.06.2021 23:50:41", 
        "VPIS": "2021-06-04 09:13:21", 
        "ZAZNALI": "1"
    }, 
    {
        "DEPTH": "4", 
        "EMS_NUM": null, 
        "FELT": "0", 
        "GEOLOC": "9 km V od Kobarida", 
        "INTENZITETA": null, 
        "LAT": "46.27", 
        "LON": "13.7", 
        "MAG1": ".6", 
        "NSTA": "14", 
        "OBJECTID": "790575", 
        "ORID": "2048330", 
        "ORIGTIME": "01-06-2021 19:50:39.30", 
        "REVISION": "1", 
        "TIME": "01.06.2021 19:50:39", 
        "VPIS": "2021-06-04 09:13:16", 
        "ZAZNALI": "0"
    }, 
    {
        "DEPTH": "18", 
        "EMS_NUM": null, 
        "FELT": "1", 
        "GEOLOC": "56 km JV od Zagreba (Hrva\u0161ka)", 
        "INTENZITETA": null, 
        "LAT": "45.37", 
        "LON": "16.33", 
        "MAG1": "3.4", 
        "NSTA": "18", 
        "OBJECTID": "790435", 
        "ORID": "2047193", 
        "ORIGTIME": "01-06-2021 03:07:35.50", 
        "REVISION": "1", 
        "TIME": "01.06.2021 03:07:35", 
        "VPIS": "2021-06-08 08:48:02", 
        "ZAZNALI": "2"
    }, 
    {
        "DEPTH": "11", 
        "EMS_NUM": null, 
        "FELT": "1", 
        "GEOLOC": "3 km SZ od Trbovelj", 
        "INTENZITETA": null, 
        "LAT": "46.17", 
        "LON": "15.03", 
        "MAG1": ".7", 
        "NSTA": "22", 
        "OBJECTID": "790415", 
        "ORID": "2047137", 
        "ORIGTIME": "01-06-2021 02:39:37.50", 
        "REVISION": "1", 
        "TIME": "01.06.2021 02:39:37", 
        "VPIS": "2021-06-04 09:12:57", 
        "ZAZNALI": "1"
    }, 
    {
        "DEPTH": "15", 
        "EMS_NUM": null, 
        "FELT": "1", 
        "GEOLOC": "11 km SV od Humina (Gemona Del Friuli, Italija)", 
        "INTENZITETA": null, 
        "LAT": "46.32", 
        "LON": "13.26", 
        "MAG1": "2", 
        "NSTA": "7", 
        "OBJECTID": "790355", 
        "ORID": "2046625", 
        "ORIGTIME": "31-05-2021 07:12:23.60", 
        "REVISION": "1", 
        "TIME": "31.05.2021 07:12:23", 
        "VPIS": "2021-06-01 13:03:15", 
        "ZAZNALI": "3"
    }, 
    {
        "DEPTH": "18", 
        "EMS_NUM": null, 
        "FELT": "1", 
        "GEOLOC": "4 km V od \u0160kofje Loke", 
        "INTENZITETA": null, 
        "LAT": "46.16", 
        "LON": "14.36", 
        "MAG1": "1.3", 
        "NSTA": "22", 
        "OBJECTID": "790335", 
        "ORID": "2046131", 
        "ORIGTIME": "31-05-2021 03:06:14.30", 
        "REVISION": "1", 
        "TIME": "31.05.2021 03:06:14", 
        "VPIS": "2021-06-01 13:03:10", 
        "ZAZNALI": "2"
    }, 
    {
        "DEPTH": "9", 
        "EMS_NUM": null, 
        "FELT": "0", 
        "GEOLOC": "7 km Z od \u0160marja pri Jel\u0161ah", 
        "INTENZITETA": null, 
        "LAT": "46.23", 
        "LON": "15.43", 
        "MAG1": ".7", 
        "NSTA": "15", 
        "OBJECTID": "790275", 
        "ORID": "2045836", 
        "ORIGTIME": "30-05-2021 18:10:57.80", 
        "REVISION": "1", 
        "TIME": "30.05.2021 18:10:57", 
        "VPIS": "2021-05-31 15:41:33", 
        "ZAZNALI": "0"
    }, 
    {
        "DEPTH": "9", 
        "EMS_NUM": null, 
        "FELT": "0", 
        "GEOLOC": "6 km Z od \u0160marja pri Jel\u0161ah", 
        "INTENZITETA": null, 
        "LAT": "46.23", 
        "LON": "15.44", 
        "MAG1": ".8", 
        "NSTA": "15", 
        "OBJECTID": "790399", 
        "ORID": null, 
        "ORIGTIME": "30-05-2021 18:08:47.70", 
        "REVISION": "1", 
        "TIME": "30.05.2021 18:08:47", 
        "VPIS": "2021-05-31 15:41:29", 
        "ZAZNALI": "0"
    }, 
    {
        "DEPTH": "4", 
        "EMS_NUM": null, 
        "FELT": "0", 
        "GEOLOC": "3 km SV od Bizeljskega", 
        "INTENZITETA": null, 
        "LAT": "46.03", 
        "LON": "15.73", 
        "MAG1": ".6", 
        "NSTA": "12", 
        "OBJECTID": "790215", 
        "ORID": "2044918", 
        "ORIGTIME": "30-05-2021 03:23:25.40", 
        "REVISION": "1", 
        "TIME": "30.05.2021 03:23:25", 
        "VPIS": "2021-05-31 15:41:11", 
        "ZAZNALI": "0"
    }, 
    {
        "DEPTH": "9", 
        "EMS_NUM": null, 
        "FELT": "0", 
        "GEOLOC": "7 km V od Kamnika", 
        "INTENZITETA": null, 
        "LAT": "46.23", 
        "LON": "14.71", 
        "MAG1": ".6", 
        "NSTA": "12", 
        "OBJECTID": "790501", 
        "ORID": null, 
        "ORIGTIME": "29-05-2021 05:16:28.00", 
        "REVISION": "1", 
        "TIME": "29.05.2021 05:16:28", 
        "VPIS": "2021-06-01 11:23:36", 
        "ZAZNALI": "0"
    }, 
    {
        "DEPTH": "9", 
        "EMS_NUM": null, 
        "FELT": "0", 
        "GEOLOC": "8 km V od Kamnika", 
        "INTENZITETA": null, 
        "LAT": "46.23", 
        "LON": "14.72", 
        "MAG1": ".7", 
        "NSTA": "13", 
        "OBJECTID": "790500", 
        "ORID": null, 
        "ORIGTIME": "29-05-2021 05:15:07.30", 
        "REVISION": "1", 
        "TIME": "29.05.2021 05:15:07", 
        "VPIS": "2021-06-01 11:23:30", 
        "ZAZNALI": "0"
    }, 
    {
        "DEPTH": "9", 
        "EMS_NUM": null, 
        "FELT": "0", 
        "GEOLOC": "7 km V od Kamnika", 
        "INTENZITETA": null, 
        "LAT": "46.24", 
        "LON": "14.71", 
        "MAG1": ".7", 
        "NSTA": "10", 
        "OBJECTID": "790498", 
        "ORID": null, 
        "ORIGTIME": "29-05-2021 05:04:35.90", 
        "REVISION": "1", 
        "TIME": "29.05.2021 05:04:35", 
        "VPIS": "2021-06-01 11:23:17", 
        "ZAZNALI": "0"
    }, 
    {
        "DEPTH": "13", 
        "EMS_NUM": null, 
        "FELT": "1", 
        "GEOLOC": "5 km J od Mozirja", 
        "INTENZITETA": "IV", 
        "LAT": "46.29", 
        "LON": "14.95", 
        "MAG1": "1.8", 
        "NSTA": "34", 
        "OBJECTID": "790135", 
        "ORID": "2043861", 
        "ORIGTIME": "28-05-2021 23:02:32.00", 
        "REVISION": "1", 
        "TIME": "28.05.2021 23:02:32", 
        "VPIS": "2021-06-15 15:37:43", 
        "ZAZNALI": "83"
    }, 
    {
        "DEPTH": "10", 
        "EMS_NUM": null, 
        "FELT": "0", 
        "GEOLOC": "3 km S od Kne\u017eaka", 
        "INTENZITETA": null, 
        "LAT": "45.65", 
        "LON": "14.25", 
        "MAG1": "1", 
        "NSTA": "14", 
        "OBJECTID": "789915", 
        "ORID": "2041901", 
        "ORIGTIME": "27-05-2021 21:10:36.50", 
        "REVISION": "1", 
        "TIME": "27.05.2021 21:10:36", 
        "VPIS": "2021-06-01 12:59:02", 
        "ZAZNALI": "0"
    }, 
    {
        "DEPTH": "9", 
        "EMS_NUM": null, 
        "FELT": "1", 
        "GEOLOC": "2 km SZ od \u0160marje\u0161kih Toplic", 
        "INTENZITETA": "III", 
        "LAT": "45.87", 
        "LON": "15.21", 
        "MAG1": "1.4", 
        "NSTA": "35", 
        "OBJECTID": "789775", 
        "ORID": "2040370", 
        "ORIGTIME": "26-05-2021 20:53:54.60", 
        "REVISION": "1", 
        "TIME": "26.05.2021 20:53:54", 
        "VPIS": "2021-06-01 12:38:47", 
        "ZAZNALI": "69"
    }, 
    {
        "DEPTH": "9", 
        "EMS_NUM": null, 
        "FELT": "0", 
        "GEOLOC": "4 km J od Kranja", 
        "INTENZITETA": null, 
        "LAT": "46.21", 
        "LON": "14.35", 
        "MAG1": ".3", 
        "NSTA": "9", 
        "OBJECTID": "790075", 
        "ORID": null, 
        "ORIGTIME": "26-05-2021 01:03:37.70", 
        "REVISION": "1", 
        "TIME": "26.05.2021 01:03:37", 
        "VPIS": "2021-06-01 12:38:09", 
        "ZAZNALI": "0"
    }, 
    {
        "DEPTH": "7", 
        "EMS_NUM": null, 
        "FELT": "0", 
        "GEOLOC": "3 km Z od Beljaka (Villach, Avstrija)", 
        "INTENZITETA": null, 
        "LAT": "46.63", 
        "LON": "13.81", 
        "MAG1": "1.3", 
        "NSTA": "14", 
        "OBJECTID": "789675", 
        "ORID": "2039371", 
        "ORIGTIME": "26-05-2021 00:19:26.70", 
        "REVISION": "1", 
        "TIME": "26.05.2021 00:19:26", 
        "VPIS": "2021-06-01 12:38:03", 
        "ZAZNALI": "0"
    }, 
    {
        "DEPTH": "7", 
        "EMS_NUM": null, 
        "FELT": "1", 
        "GEOLOC": "8 km SV od Vinice pri \u010crnomlju", 
        "INTENZITETA": "III", 
        "LAT": "45.49", 
        "LON": "15.35", 
        "MAG1": "1.4", 
        "NSTA": "8", 
        "OBJECTID": "789595", 
        "ORID": "2038595", 
        "ORIGTIME": "25-05-2021 00:58:01.70", 
        "REVISION": "1", 
        "TIME": "25.05.2021 00:58:01", 
        "VPIS": "2021-06-01 12:23:11", 
        "ZAZNALI": "4"
    }, 
    {
        "DEPTH": "9", 
        "EMS_NUM": null, 
        "FELT": "0", 
        "GEOLOC": "3 km SZ od Beljaka (Villach, Avstrija)", 
        "INTENZITETA": null, 
        "LAT": "46.64", 
        "LON": "13.83", 
        "MAG1": ".8", 
        "NSTA": "4", 
        "OBJECTID": "789615", 
        "ORID": null, 
        "ORIGTIME": "24-05-2021 10:09:41.00", 
        "REVISION": "1", 
        "TIME": "24.05.2021 10:09:41", 
        "VPIS": "2021-05-25 11:32:13", 
        "ZAZNALI": "0"
    }
]